get_py_deps-3.0.0.dist-info/METADATA
get_py_deps-3.0.0.dist-info/WHEEL
get_py_deps-3.0.0.dist-info/entry_points.txt
get_py_deps-3.0.0.dist-info/licenses/LICENSE
get_py_deps/__init__.py
get_py_deps/main.py
get_py_deps-3.0.0.dist-info/RECORD
