Metadata-Version: 2.1
Name: get-py-deps
Version: 3.0.0
Project-URL: Repository, https://github.com/Wesztman/get-py-deps
Requires-Python: >=3.10
Requires-Dist: prettytable~=3.10.0
Requires-Dist: setuptools~=69.1.1
Requires-Dist: ruff~=0.2.1; extra == "lint"
Requires-Dist: mypy~=1.8.0; extra == "lint"
Requires-Dist: types-setuptools~=69.1.0.20240229; extra == "lint"
Requires-Dist: pyright~=1.1.352; extra == "lint"
Requires-Dist: pytest~=8.0.0; extra == "test"
Requires-Dist: pytest-cov~=4.1.0; extra == "test"
Requires-Dist: coverage[toml]~=7.4.1; extra == "test"
Requires-Dist: pre-commit~=3.6.1; extra == "dev"
Requires-Dist: get-py-deps[lint]; extra == "dev"
Requires-Dist: get-py-deps[test]; extra == "dev"
Provides-Extra: lint
Provides-Extra: test
Provides-Extra: dev
